pygame_list_visualizer/__init__.py
pygame_list_visualizer/main.py
pygame_list_visualizer-0.0.2.dist-info/licenses/LICENSE
pygame_list_visualizer-0.0.2.dist-info/METADATA
pygame_list_visualizer-0.0.2.dist-info/WHEEL
pygame_list_visualizer-0.0.2.dist-info/top_level.txt
pygame_list_visualizer-0.0.2.dist-info/RECORD
