Metadata-Version: 2.4
Name: pygame_list_visualizer
Version: 0.0.2
License-File: LICENSE
Requires-Dist: pygame-ce
Dynamic: description
Dynamic: description-content-type
Dynamic: license-file
Dynamic: requires-dist
